{
    "events": [
      {
        "Name": "Mental health day",
        "Date": "10/05/2026",
        "Time": "10:00 - 15:00",
        "Location": "Belfast BC-Building foyer",
        "Desc": "Mental health day in the belfast campus. There will be several stalls and speakers in the BC building foyer for the students that are would like to learn more about mental health.",
        "Img":"/StudentLife/Resources/images/mentalHealthDay.webp",
        "alt":"../Resources/images/mentalHealthDay.webp"
      },
      {
        "Name": "Tea and coffee",
        "Date": "14/05/2026",
        "Time": "13:00 - 14:00",
        "Location": "Ballymena BM-Building sixth floor",
        "Desc": "Free tea and coffee. there will be a selection of refreshments including hot drinks and food, all students are welcome.",
        "Img":"/StudentLife/Resources/images/teaCoffee.webp",
        "alt":"../Resources/images/teaCoffee.webp"
      },
      {
        "Name": "University open day",
        "Date": "03/06/2026",
        "Time": "17:00 - 21:00",
        "Location": "Edinburgh campus",
        "Desc": "A university open day for all students who would like to learn more about our university, students can arrive from anytime between 17:00 - 19:00 and are welcome to explore the campus with a tour or at their own leisure.",
        "Img":"/StudentLife/Resources/images/Edinburgh.png",
        "alt":"../Resources/images/Edinburgh.png"
      },
      {
        "Name": "Careers day for engineering students",
        "Date": "17/06/2026",
        "Time": "12:00 - 15:00",
        "Location": "Belfast BD-Building ground floor",
        "Desc": "A careers day for the engineering students, several top companies will be in to give students an oppurtunity to see what their career propspects are for the future",
        "Img":"/StudentLife/Resources/images/engineering.webp",
        "alt":"../Resources/images/engineering.webp"
      },
      {
        "Name": "University football match",
        "Date": "20/06/2026",
        "Time": "13:00 - 15:00",
        "Location": "Beijing campus football pitch",
        "Desc": "A friendly student football match between two teams of our physical education students, all students are welcome to watch the match",
        "Img":"/StudentLife/Resources/images/Football.png",
        "alt":"../Resources/images/Football.png"
      }
    ]
  }